{
  "routes": [
    {
      "method": "GET",
      "path": "/evnts",
      "handler": "evnt.find",
      "config": {
        "policies": []
      }
    },
    {
      "method": "GET",
      "path": "/evnts/count",
      "handler": "evnt.count",
      "config": {
        "policies": []
      }
    },
    {
      "method": "GET",
      "path": "/evnts/:id",
      "handler": "evnt.findOne",
      "config": {
        "policies": []
      }
    },
    {
      "method": "POST",
      "path": "/evnts",
      "handler": "evnt.create",
      "config": {
        "policies": []
      }
    },
    {
      "method": "PUT",
      "path": "/evnts/:id",
      "handler": "evnt.update",
      "config": {
        "policies": []
      }
    },
    {
      "method": "DELETE",
      "path": "/evnts/:id",
      "handler": "evnt.delete",
      "config": {
        "policies": []
      }
    }
  ]
}
